<?xml version="1.0" encoding="utf-8"?>
<animNode>
	<m_Name>pvFix0_aim_down</m_Name>
	<m_AnimName>Bob_IdleDriving</m_AnimName>
	<m_deferredBoneAxis>Y</m_deferredBoneAxis>
	<m_SyncTrackingEnabled>false</m_SyncTrackingEnabled>
	<m_SpeedScale>IdleSpeed</m_SpeedScale>
	<m_BlendTime>0.30</m_BlendTime>
	<m_maxTorsoTwist>70.0</m_maxTorsoTwist>
	<m_Conditions>
		<m_Name>KI5vehicle</m_Name>
		<m_Type>STRING</m_Type>
		<m_StringValue>True</m_StringValue>
	</m_Conditions>
	<m_Conditions>
		<m_Name>bAimAtFloor</m_Name>
		<m_Type>BOOL</m_Type>
		<m_BoolValue>true</m_BoolValue>
	</m_Conditions>
</animNode>