<?xml version="1.0" encoding="utf-8"?>
<clothingItem>
	<m_MaleModel>Skinned\Clothes\Spongie\M_TrousersTucked</m_MaleModel>
	<m_FemaleModel>Skinned\Clothes\Spongie\F_TrousersTucked</m_FemaleModel>
	<m_GUID>fb9618f1-f7d6-4a7d-ae18-83b20a8a72b9</m_GUID>
	<m_Static>false</m_Static>
	<m_AllowRandomHue>false</m_AllowRandomHue>
	<m_AllowRandomTint>false</m_AllowRandomTint>
	<m_AttachBone></m_AttachBone>
	<m_Masks>14</m_Masks>
	<m_Masks>15</m_Masks>
	<textureChoices>Clothes\Trousers_Mesh\TrousersMesh_Fire_Formal_Meade</textureChoices>
</clothingItem>